{
    "rightText": "All the information posted is for information purposes only and under no circumstances is a public offer, defined by the provisions of the Civil Code of the Russian Federation, does not contain an accurate and complete description and characteristics of the object, and may be subject to change. The user is notified that any materials posted on the website are the intellectual property of HPP Construction LLC (the right holder). The User has no right to perform any actions with the intellectual property objects without prior written permission of the right holder, otherwise, the right holder reserves the right to levy fines, stipulated by Russian legislation, as well as to apply to competent authorities for protection of their rights and legitimate interests.",
    "copyright": "GES Construction © 2024",
    "leftTitle": "Ответим на ваши </br> вопросы",
    "politicHref": "/politic",
    "politicText": "Политика конфиденциальности",
    "contactsText": "Свяжитесь с нами",
    "contactsHref": "/contacts",
    "menuList": [
        {
            "linkText": "О компании",
            "href": "/about"
        },
        {
            "linkText": "Карьера",
            "href": "/career"
        },
        {
            "linkText": "Документы",
            "href": "/documents"
        },
        {
            "linkText": "Услуги",
            "href": "/services"
        },
        {
            "linkText": "Контакты",
            "href": "/contacts"
        },
        {
            "linkText": "Пресс-центр",
            "href": "/press-center"
        },
        {
            "linkText": "Проекты",
            "href": "/projects"
        }
    ]
}
